biomcp/__init__.py
biomcp/cli/__init__.py
biomcp/cli/cli.py
biomcp-0.0.1.dist-info/METADATA
biomcp-0.0.1.dist-info/WHEEL
biomcp-0.0.1.dist-info/entry_points.txt
biomcp-0.0.1.dist-info/licenses/LICENSE
biomcp-0.0.1.dist-info/RECORD
